{
  "attempt_count": 1,
  "document": {
    "block_id": "search-b06",
    "results": [
      {
        "answer": [
          "-3",
          "-78",
          "0",
          "-103",
          "-3"
        ],
        "case_id": "S061",
        "check_summary": "Unable to verify a unique allowed mechanism from the supplied prefix.",
        "confidence": 0.05,
        "rule_summary": "Unresolved."
      },
      {
        "answer": [
          "0",
          "0",
          "0",
          "0",
          "0"
        ],
        "case_id": "S062",
        "check_summary": "Unable to verify a unique allowed mechanism from the supplied prefix.",
        "confidence": 0.02,
        "rule_summary": "Unresolved."
      },
      {
        "answer": [
          "0",
          "0",
          "0",
          "0",
          "0"
        ],
        "case_id": "S063",
        "check_summary": "Unable to verify a unique allowed mechanism from the supplied prefix.",
        "confidence": 0.02,
        "rule_summary": "Unresolved."
      },
      {
        "answer": [
          "0",
          "0",
          "0",
          "0",
          "0"
        ],
        "case_id": "S064",
        "check_summary": "Unable to verify a unique allowed mechanism from the supplied prefix.",
        "confidence": 0.02,
        "rule_summary": "Unresolved."
      },
      {
        "answer": [
          "-32",
          "24",
          "-36",
          "26",
          "-40"
        ],
        "case_id": "S065",
        "check_summary": "Odd-position stream decreases by 4; even-position stream increases by 2.",
        "confidence": 0.99,
        "rule_summary": "Two interleaved arithmetic streams."
      },
      {
        "answer": [
          "0",
          "0",
          "0",
          "0",
          "0"
        ],
        "case_id": "S066",
        "check_summary": "Unable to verify a unique allowed mechanism from the supplied prefix.",
        "confidence": 0.02,
        "rule_summary": "Unresolved."
      },
      {
        "answer": [
          "0",
          "0",
          "0",
          "0",
          "0"
        ],
        "case_id": "S067",
        "check_summary": "Unable to verify a unique allowed mechanism from the supplied prefix.",
        "confidence": 0.02,
        "rule_summary": "Unresolved."
      },
      {
        "answer": [
          "0",
          "0",
          "0",
          "0",
          "0"
        ],
        "case_id": "S068",
        "check_summary": "Unable to verify a unique allowed mechanism from the supplied prefix.",
        "confidence": 0.02,
        "rule_summary": "Unresolved."
      },
      {
        "answer": [
          "0",
          "0",
          "0",
          "0",
          "0"
        ],
        "case_id": "S069",
        "check_summary": "Unable to verify a unique allowed mechanism from the supplied prefix.",
        "confidence": 0.02,
        "rule_summary": "Unresolved."
      },
      {
        "answer": [
          "-3",
          "-78",
          "0",
          "-103",
          "-3"
        ],
        "case_id": "S070",
        "check_summary": "Odd positions alternate -3 and 0; even-position values have successive differences decreasing by 3, giving the next values -78 and -103.",
        "confidence": 0.98,
        "rule_summary": "Two interleaved streams: periodic constants and a quadratic even-position stream."
      },
      {
        "answer": [
          "0",
          "0",
          "0",
          "0",
          "0"
        ],
        "case_id": "S071",
        "check_summary": "Unable to verify a unique allowed mechanism from the supplied prefix.",
        "confidence": 0.02,
        "rule_summary": "Unresolved."
      },
      {
        "answer": [
          "-29",
          "-33",
          "-20",
          "-24",
          "-28"
        ],
        "case_id": "S072",
        "check_summary": "Growing arithmetic blocks: block starts rise by 3 and each block steps by -4; the next block continues then starts at -20.",
        "confidence": 0.97,
        "rule_summary": "GROWBLOCK with block lengths 2, 3, 4, 5, ..."
      }
    ],
    "schema_version": "4.0"
  },
  "job_id": "search-round-03-G-2B08D2BA7D25-search-b06-proposer-6",
  "outcome": "valid_output",
  "response_sha256": "9321bbfda54eea84f8bb9ec828c2094f6c56eb7f1b4ec6cfc8fec26ec0e6ecf9",
  "terminal_artifact_relpath": "jobs/search-round-03-G-2B08D2BA7D25-search-b06-proposer-6/attempt-01"
}
