{
  "attempt_count": 1,
  "document": {
    "block_id": "search-b07",
    "results": [
      {
        "answer": [
          "-35",
          "-38",
          "-42",
          "-45",
          "-49"
        ],
        "case_id": "S073",
        "check_summary": "Alternating differences -4,-3 replay the full prefix.",
        "confidence": 0.99,
        "rule_summary": "Periodic polynomial delta."
      },
      {
        "answer": [
          "9322",
          "-15063",
          "24386",
          "-39461",
          "63938"
        ],
        "case_id": "S074",
        "check_summary": "Extrapolated from the apparent alternating linear recurrence pattern.",
        "confidence": 0.22,
        "rule_summary": "Phase-specific affine/linear recurrence."
      },
      {
        "answer": [
          "8",
          "10",
          "6",
          "8",
          "9"
        ],
        "case_id": "S075",
        "check_summary": "Interleaved subsequences identified approximately.",
        "confidence": 0.16,
        "rule_summary": "Interleaved polynomial or affine streams."
      },
      {
        "answer": [
          "-14337",
          "-20656",
          "-28321",
          "-37502",
          "-48201"
        ],
        "case_id": "S076",
        "check_summary": "Extrapolated from nonlinear growing differences.",
        "confidence": 0.14,
        "rule_summary": "Periodic polynomial delta."
      },
      {
        "answer": [
          "-4053",
          "-9778",
          "-23575",
          "-56811",
          "-136852"
        ],
        "case_id": "S077",
        "check_summary": "Extrapolated from the apparent multiplicative growth pattern.",
        "confidence": 0.18,
        "rule_summary": "Phase-specific affine recurrence."
      },
      {
        "answer": [
          "-4915828",
          "14747489",
          "-44242462",
          "132727391",
          "-398182168"
        ],
        "case_id": "S078",
        "check_summary": "Exact replay under x_next=-3x+5.",
        "confidence": 1.0,
        "rule_summary": "Affine recurrence."
      },
      {
        "answer": [
          "84",
          "100",
          "138",
          "145",
          "180"
        ],
        "case_id": "S079",
        "check_summary": "Extrapolated from the apparent interleaved pattern.",
        "confidence": 0.12,
        "rule_summary": "Interleaved polynomial or affine streams."
      },
      {
        "answer": [
          "-408434",
          "408426",
          "1225270",
          "-3675812",
          "33082206"
        ],
        "case_id": "S080",
        "check_summary": "Three interleaved streams each follow multiplier 9 with phase-specific bias.",
        "confidence": 0.99,
        "rule_summary": "Three-stream interleave with affine updates."
      },
      {
        "answer": [
          "38094",
          "-304742",
          "-152370",
          "1218970",
          "609485"
        ],
        "case_id": "S081",
        "check_summary": "Odd and even subsequences follow multiplier -4 with phase-specific bias.",
        "confidence": 0.99,
        "rule_summary": "Two-stream interleave with affine updates."
      },
      {
        "answer": [
          "-388",
          "-509",
          "-653",
          "-822",
          "-1018"
        ],
        "case_id": "S082",
        "check_summary": "Successive deltas are negative squares.",
        "confidence": 1.0,
        "rule_summary": "Polynomial delta sequence."
      },
      {
        "answer": [
          "-2765",
          "-4008",
          "-5613",
          "-7643",
          "-10158"
        ],
        "case_id": "S083",
        "check_summary": "Finite differences support a constant fourth difference after the initial terms.",
        "confidence": 0.96,
        "rule_summary": "Integer-valued polynomial."
      },
      {
        "answer": [
          "-349887",
          "836373",
          "-1997571",
          "4778440",
          "-11428353"
        ],
        "case_id": "S084",
        "check_summary": "Extrapolated from the apparent alternating growth recurrence.",
        "confidence": 0.12,
        "rule_summary": "Phase-specific affine recurrence."
      }
    ],
    "schema_version": "4.0"
  },
  "job_id": "search-round-04-G-335AFD967606-search-b07-proposer-1",
  "outcome": "valid_output",
  "response_sha256": "8d5f6b6fcbf8d9862df4ad8df9aa334f6b73820874a0c44ff16847b7534cdb19",
  "terminal_artifact_relpath": "jobs/search-round-04-G-335AFD967606-search-b07-proposer-1/attempt-01"
}
