{
  "attempt_count": 1,
  "document": {
    "block_id": "final-b02",
    "results": [
      {
        "answer": [
          "-78",
          "-32",
          "27",
          "-105",
          "64"
        ],
        "case_id": "F013",
        "check_summary": "Three interleaved streams: arithmetic, quadratic-step, and alternating-power increments.",
        "confidence": 0.86,
        "rule_summary": "INTERLEAVE"
      },
      {
        "answer": [
          "-74",
          "-61",
          "-48",
          "-35",
          "-22"
        ],
        "case_id": "F014",
        "check_summary": "Growing arithmetic blocks with starts and steps following polynomial progressions.",
        "confidence": 0.78,
        "rule_summary": "GROWBLOCK"
      },
      {
        "answer": [
          "53",
          "71",
          "89",
          "107",
          "125"
        ],
        "case_id": "F015",
        "check_summary": "Arithmetic block continuation inferred from the visible phase progression.",
        "confidence": 0.34,
        "rule_summary": "GROWBLOCK"
      },
      {
        "answer": [
          "-4",
          "-7",
          "45",
          "-13",
          "-12"
        ],
        "case_id": "F016",
        "check_summary": "Phase-dependent recurrence extrapolation from the observed irregular prefix.",
        "confidence": 0.12,
        "rule_summary": "PDELTA"
      },
      {
        "answer": [
          "-101",
          "-69",
          "-136",
          "-42",
          "-181"
        ],
        "case_id": "F017",
        "check_summary": "Alternating phase recurrence extrapolation.",
        "confidence": 0.11,
        "rule_summary": "AFFINE"
      },
      {
        "answer": [
          "18",
          "74",
          "-8",
          "86",
          "-25"
        ],
        "case_id": "F018",
        "check_summary": "Periodic affine-style continuation of the observed phase pattern.",
        "confidence": 0.1,
        "rule_summary": "MODAFFINE"
      },
      {
        "answer": [
          "56",
          "17",
          "74",
          "25",
          "92"
        ],
        "case_id": "F019",
        "check_summary": "Phase-specific affine continuation.",
        "confidence": 0.1,
        "rule_summary": "AFFINE"
      },
      {
        "answer": [
          "-44",
          "46",
          "27",
          "-66",
          "64"
        ],
        "case_id": "F020",
        "check_summary": "Three interleaved polynomial-difference streams.",
        "confidence": 0.9,
        "rule_summary": "INTERLEAVE"
      },
      {
        "answer": [
          "-33",
          "-38",
          "-43",
          "-27",
          "-32"
        ],
        "case_id": "F021",
        "check_summary": "Mostly constant phase deltas with polynomially increasing wrap increments.",
        "confidence": 0.58,
        "rule_summary": "PDELTA"
      },
      {
        "answer": [
          "-16",
          "83",
          "-34",
          "116",
          "-52"
        ],
        "case_id": "F022",
        "check_summary": "Periodic modular-affine continuation inferred from the irregular prefix.",
        "confidence": 0.1,
        "rule_summary": "MODAFFINE"
      },
      {
        "answer": [
          "14",
          "-6",
          "15",
          "-8",
          "16"
        ],
        "case_id": "F023",
        "check_summary": "Odd positions increase by one; even positions decrease by two.",
        "confidence": 0.99,
        "rule_summary": "INTERLEAVE"
      },
      {
        "answer": [
          "-123",
          "113",
          "-160",
          "144",
          "-201"
        ],
        "case_id": "F024",
        "check_summary": "Alternating phase polynomial continuation.",
        "confidence": 0.1,
        "rule_summary": "INTERLEAVE"
      }
    ],
    "schema_version": "3.0"
  },
  "job_id": "final-G-1407BDDB752D-final-b02-proposer-02",
  "outcome": "valid_output",
  "response_sha256": "b4015a9333c73b435f509a079bd8e709fe8a0afb23a584c603de3327e8eb5138",
  "terminal_artifact_relpath": "jobs/final-G-1407BDDB752D-final-b02-proposer-02/attempt-01"
}
