{
  "attempt_count": 1,
  "document": {
    "block_id": "search-b07",
    "results": [
      {
        "answer": [
          "-35",
          "-38",
          "-42",
          "-45",
          "-49"
        ],
        "case_id": "S073",
        "check_summary": "Alternating differences -4,-3 replay the prefix.",
        "confidence": 0.99,
        "rule_summary": "Periodic first-order delta."
      },
      {
        "answer": [
          "9345",
          "-15126",
          "24471",
          "-39597",
          "64068"
        ],
        "case_id": "S074",
        "check_summary": "Signed near-Fibonacci continuation.",
        "confidence": 0.35,
        "rule_summary": "Phase-dependent linear recurrence."
      },
      {
        "answer": [
          "8",
          "6",
          "10",
          "8",
          "15"
        ],
        "case_id": "S075",
        "check_summary": "Interleaved-stream continuation estimate.",
        "confidence": 0.2,
        "rule_summary": "Interleaved polynomial streams."
      },
      {
        "answer": [
          "-14125",
          "-20239",
          "-27280",
          "-35869",
          "-46176"
        ],
        "case_id": "S076",
        "check_summary": "Nonlinear-growth continuation estimate.",
        "confidence": 0.2,
        "rule_summary": "Phase-dependent polynomial deltas."
      },
      {
        "answer": [
          "-4069",
          "-9830",
          "-23725",
          "-57248",
          "-138181"
        ],
        "case_id": "S077",
        "check_summary": "Accelerating recurrence continuation estimate.",
        "confidence": 0.25,
        "rule_summary": "Phase-dependent linear recurrence."
      },
      {
        "answer": [
          "-4915828",
          "14747489",
          "-44242462",
          "132727391",
          "-398182168"
        ],
        "case_id": "S078",
        "check_summary": "Exact affine map x -> -3x+5.",
        "confidence": 0.99,
        "rule_summary": "Periodic affine update."
      },
      {
        "answer": [
          "91",
          "121",
          "148",
          "191",
          "230"
        ],
        "case_id": "S079",
        "check_summary": "Growing-block continuation estimate.",
        "confidence": 0.2,
        "rule_summary": "Growing arithmetic blocks."
      },
      {
        "answer": [
          "1225270",
          "-3675812",
          "408426",
          "11027404",
          "-33082214"
        ],
        "case_id": "S080",
        "check_summary": "Three interleaved affine streams replay exactly.",
        "confidence": 0.99,
        "rule_summary": "Three-stream interleave with multiplier 9."
      },
      {
        "answer": [
          "-152370",
          "304738",
          "-609474",
          "1218946",
          "-2437894"
        ],
        "case_id": "S081",
        "check_summary": "Alternating affine updates with biases +2,-2.",
        "confidence": 0.99,
        "rule_summary": "Periodic affine update."
      },
      {
        "answer": [
          "-388",
          "-509",
          "-653",
          "-822",
          "-1018"
        ],
        "case_id": "S082",
        "check_summary": "Successive differences are negative squares.",
        "confidence": 0.99,
        "rule_summary": "Polynomial delta sequence."
      },
      {
        "answer": [
          "-2765",
          "-4008",
          "-5613",
          "-7643",
          "-10166"
        ],
        "case_id": "S083",
        "check_summary": "Finite-difference continuation estimate.",
        "confidence": 0.45,
        "rule_summary": "Integer-valued polynomial-like delta process."
      },
      {
        "answer": [
          "351000",
          "-847000",
          "2046000",
          "-4940000",
          "11920000"
        ],
        "case_id": "S084",
        "check_summary": "Alternating exponential continuation estimate.",
        "confidence": 0.25,
        "rule_summary": "Periodic affine recurrence."
      }
    ],
    "schema_version": "4.0"
  },
  "job_id": "search-round-04-G-F3EA0DB4CF72-search-b07-proposer-6",
  "outcome": "valid_output",
  "response_sha256": "829bd88bfc6d5aab5a4cb4c42996055daf64a2181986ccefb79238a62bc5824e",
  "terminal_artifact_relpath": "jobs/search-round-04-G-F3EA0DB4CF72-search-b07-proposer-6/attempt-01"
}
